apple_season/__init__.py
apple_season/apple.py
apple_season/assets.py
apple_season/basket.py
apple_season/caught.wav
apple_season/coords.py
apple_season/game.py
apple_season/main.py
Terminal_Apple_Season-1.2.8.dist-info/LICENSE.txt
Terminal_Apple_Season-1.2.8.dist-info/METADATA
Terminal_Apple_Season-1.2.8.dist-info/WHEEL
Terminal_Apple_Season-1.2.8.dist-info/top_level.txt
Terminal_Apple_Season-1.2.8.dist-info/RECORD
