Metadata-Version: 2.1
Name: Terminal-Apple-Season
Version: 1.2.8
Summary: Apple season game for terminal
Home-page: https://github.com/lol-cubes/Terminal-Apple-Season
Author: Arin Khare
Author-email: arinmkhare@gmail.com
License: UNKNOWN
Platform: UNKNOWN
Classifier: Programming Language :: Python :: 3
Classifier: License :: OSI Approved :: MIT License
Classifier: Operating System :: MacOS :: MacOS X
Requires-Dist: playsound
Requires-Dist: PyObjC ; platform_system == "Darwin"
Requires-Dist: PyGObject ; platform_system == "Linux"
Requires-Dist: windows-curses ; platform_system == "Windows"
